DRAM_bio-1.5.0.data/scripts/DRAM-setup.py
DRAM_bio-1.5.0.data/scripts/DRAM-v.py
DRAM_bio-1.5.0.data/scripts/DRAM.py
mag_annotator/CONFIG
mag_annotator/__init__.py
mag_annotator/annotate_bins.py
mag_annotator/annotate_vgfs.py
mag_annotator/camper_kit.py
mag_annotator/database_handler.py
mag_annotator/database_processing.py
mag_annotator/database_setup.py
mag_annotator/fasta_dup_name_test.py
mag_annotator/pull_sequences.py
mag_annotator/summarize_genomes.py
mag_annotator/summarize_vgfs.py
mag_annotator/utils.py
tests/__init__.py
tests/test_annotate_bins.py
tests/test_annotate_vgfs.py
tests/test_config_cleen.py
tests/test_database_handler.py
tests/test_database_processing.py
tests/test_database_setup.py
tests/test_summarize_genomes.py
tests/test_summarize_vgfs.py
tests/test_utils.py
DRAM_bio-1.5.0.dist-info/LICENSE
DRAM_bio-1.5.0.dist-info/METADATA
DRAM_bio-1.5.0.dist-info/WHEEL
DRAM_bio-1.5.0.dist-info/top_level.txt
DRAM_bio-1.5.0.dist-info/RECORD
