Metadata-Version: 2.1
Name: DRAM-bio
Version: 1.5.0
Summary: Distilled and Refined Annotation of Metabolism: A tool for the annotation and curation of function for microbial and viral genomes
Home-page: https://github.com/shafferm/DRAM/
Download-URL: https://github.com/shafferm/DRAM/tarball/1.5.0
Author: Michael Shaffer
Author-email: michael.t.shaffer@colostate.edu
Requires-Python: >=3
License-File: LICENSE
Requires-Dist: scikit-bio
Requires-Dist: pandas
Requires-Dist: altair
Requires-Dist: sqlalchemy
Requires-Dist: networkx
Requires-Dist: openpyxl
Requires-Dist: numpy
